pylucas/__init__.py
pylucas/_NetWork/Downloader.py
pylucas/_RPA/main.py
pylucas/fileops/__init__.py
pylucas/fileops/Class.py
pylucas/fileops/Function.py
pylucas/function/__init__.py
pylucas/function/Function.py
pylucas/log/__init__.py
pylucas/log/Class.py
pylucas/log/Function.py
pylucas/rwxl/__init__.py
pylucas/rwxl/Function.py
pylucas/struct/__init__.py
pylucas/struct/Class.py
pylucas-3.0.2.dist-info/LICENSE
pylucas-3.0.2.dist-info/METADATA
pylucas-3.0.2.dist-info/WHEEL
pylucas-3.0.2.dist-info/RECORD
