Metadata-Version: 2.3
Name: pylucas
Version: 3.0.2
Summary: Lucas' Functional Distribution, Which Integrates Some Commonly Used.
License: Copyright (c) 2018 The Python Packaging Authority
Author: LuLuLuOfficial
Author-email: xframilrainx@163.com
Requires-Python: >=3.13
Classifier: License :: Other/Proprietary License
Classifier: Programming Language :: Python :: 3
Classifier: Programming Language :: Python :: 3.13
Provides-Extra: all
Provides-Extra: fileops
Provides-Extra: log
Provides-Extra: rwxl
Requires-Dist: art (>=6.5,<7.0) ; extra == "log"
Requires-Dist: atr (>=1.0.1,<2.0.0) ; extra == "all"
Requires-Dist: pandas (>=2.3.1,<3.0.0) ; extra == "all"
Requires-Dist: pandas (>=2.3.1,<3.0.0) ; extra == "rwxl"
Requires-Dist: tomli-w (>=1.2.0,<2.0.0) ; extra == "all"
Requires-Dist: tomli-w (>=1.2.0,<2.0.0) ; extra == "fileops"
